turtle_gcode/__init__.py
turtle_gcode-0.0.1.dist-info/METADATA
turtle_gcode-0.0.1.dist-info/WHEEL
turtle_gcode-0.0.1.dist-info/licenses/LICENSE
turtle_gcode-0.0.1.dist-info/RECORD
