Metadata-Version: 2.1
Name: turtle_gcode
Version: 0.0.1
Summary: Convert turtle commands into G-Code
Project-URL: Homepage, https://github.com/313ctric/turtle_gcode
Project-URL: Bug Tracker, https://github.com/313ctric/turtle_gcode/issues
Author: Electric
License: zlib/libpng License
License-File: LICENSE
Classifier: License :: OSI Approved :: zlib/libpng License
Classifier: Operating System :: OS Independent
Classifier: Programming Language :: Python :: 3.10
Requires-Python: >=3.10
